packaged/__init__.py
packaged/__main__.py
packaged/cli.py
packaged/config.py
packaged/makeself-header.sh
packaged/makeself.sh
packaged/py.typed
packaged-0.6.1.dist-info/LICENSE
packaged-0.6.1.dist-info/METADATA
packaged-0.6.1.dist-info/WHEEL
packaged-0.6.1.dist-info/entry_points.txt
packaged-0.6.1.dist-info/top_level.txt
packaged-0.6.1.dist-info/RECORD
