Metadata-Version: 2.1
Name: packaged
Version: 0.6.1
Summary: The easiest way to ship python applications.
Home-page: https://github.com/tusharsadhwani/packaged
Author: Tushar Sadhwani
Author-email: tushar.sadhwani000@gmail.com
License: GPL-2.0-or-later
Classifier: License :: OSI Approved :: GNU General Public License v2 (GPLv2)
Classifier: Operating System :: OS Independent
Classifier: Programming Language :: Python :: 3
Classifier: Programming Language :: Python :: 3 :: Only
Classifier: Programming Language :: Python :: 3.8
Classifier: Programming Language :: Python :: 3.9
Classifier: Programming Language :: Python :: 3.10
Classifier: Programming Language :: Python :: 3.11
Classifier: Programming Language :: Python :: 3.12
Classifier: Programming Language :: Python :: Implementation :: CPython
Classifier: Typing :: Typed
Requires-Python: >=3.8
License-File: LICENSE
Requires-Dist: yen>=0.4.2
Requires-Dist: tomli>=1.1.0; python_version < "3.11"
Requires-Dist: yaspin>=2.5.0
Requires-Dist: pycify>=1.2.0
Provides-Extra: dev
Requires-Dist: black; extra == "dev"
Requires-Dist: mypy; extra == "dev"
Requires-Dist: pytest; extra == "dev"
Requires-Dist: pytest-cov; extra == "dev"
Requires-Dist: pytest-xdist; extra == "dev"
Requires-Dist: tox; extra == "dev"
